travelperk_python_api_types/__init__.py
travelperk_python_api_types/cost_centers/__init__.py
travelperk_python_api_types/cost_centers/cost_centers/__init__.py
travelperk_python_api_types/cost_centers/cost_centers/bulk_update_response.py
travelperk_python_api_types/cost_centers/cost_centers/cost_center.py
travelperk_python_api_types/cost_centers/cost_centers/cost_center_detail.py
travelperk_python_api_types/cost_centers/cost_centers/cost_centers.py
travelperk_python_api_types/cost_centers/cost_centers/user.py
travelperk_python_api_types/expenses/__init__.py
travelperk_python_api_types/expenses/billing_information.py
travelperk_python_api_types/expenses/invoice_lines/__init__.py
travelperk_python_api_types/expenses/invoice_lines/invoice_line.py
travelperk_python_api_types/expenses/invoice_lines/invoice_lines.py
travelperk_python_api_types/expenses/invoice_lines/metadata.py
travelperk_python_api_types/expenses/invoice_lines/user.py
travelperk_python_api_types/expenses/invoice_lines/vendor.py
travelperk_python_api_types/expenses/invoice_profiles/__init__.py
travelperk_python_api_types/expenses/invoice_profiles/invoice_profile.py
travelperk_python_api_types/expenses/invoice_profiles/invoice_profiles.py
travelperk_python_api_types/expenses/invoices/__init__.py
travelperk_python_api_types/expenses/invoices/invoice.py
travelperk_python_api_types/expenses/invoices/invoices.py
travelperk_python_api_types/expenses/invoices/lines.py
travelperk_python_api_types/expenses/invoices/taxes_summary.py
travelperk_python_api_types/expenses/invoices/travelperk_bank_account.py
travelperk_python_api_types/greenperk/__init__.py
travelperk_python_api_types/greenperk/greenperk/__init__.py
travelperk_python_api_types/greenperk/greenperk/emission_value.py
travelperk_python_api_types/greenperk/greenperk/emissions.py
travelperk_python_api_types/greenperk/greenperk/hotel_emissions.py
travelperk_python_api_types/scim/__init__.py
travelperk_python_api_types/scim/users/__init__.py
travelperk_python_api_types-1.2.0.dist-info/LICENSE
travelperk_python_api_types-1.2.0.dist-info/METADATA
travelperk_python_api_types-1.2.0.dist-info/WHEEL
travelperk_python_api_types-1.2.0.dist-info/top_level.txt
travelperk_python_api_types-1.2.0.dist-info/RECORD
