Metadata-Version: 2.1
Name: travelperk-python-api-types
Version: 1.2.0
Summary: Python types for the travelperk API entities
Home-page: https://github.com/namelivia/travelperk-python-api-types
Author: José Ignacio Amelivia Santiago
Author-email: jignacio.amelivia@gmail.com
Project-URL: Bug Reports, https://github.com/namelivia/travelperk-python-api-types/issues
Keywords: travelperk,api
Classifier: Development Status :: 5 - Production/Stable
Classifier: Intended Audience :: Developers
Classifier: Topic :: Software Development :: Build Tools
Classifier: License :: OSI Approved :: MIT License
Classifier: Programming Language :: Python :: 3.8
Classifier: Programming Language :: Python :: 3.9
Requires-Python: >=3.6, <4
License-File: LICENSE
Requires-Dist: pydantic
